boolia/__init__.py
boolia/api.py
boolia/ast.py
boolia/errors.py
boolia/functions.py
boolia/lexer.py
boolia/operators.py
boolia/parser.py
boolia/py.typed
boolia/resolver.py
boolia/serialization.py
boolia-0.1.3.dist-info/METADATA
boolia-0.1.3.dist-info/WHEEL
boolia-0.1.3.dist-info/licenses/LICENSE
boolia-0.1.3.dist-info/RECORD
