Metadata-Version: 2.4
Name: boolia
Version: 0.1.3
Summary: Tiny, safe boolean-expression language with dotted paths, functions, and rule books.
Project-URL: Homepage, https://github.com/joaofreires/boolia
Project-URL: Repository, https://github.com/joaofreires/boolia
Project-URL: Documentation, https://github.com/joaofreires/boolia#readme
Project-URL: Issues, https://github.com/joaofreires/boolia/issues
Project-URL: Changelog, https://github.com/joaofreires/boolia/releases
Author-email: João Freires <joaofreires@tutanota.com>
Maintainer-email: João Freires <joaofreires@tutanota.com>
License: MIT
License-File: LICENSE
Keywords: boolean,dsl,expression,jinja-like,logic,rules
Classifier: License :: OSI Approved :: MIT License
Classifier: Programming Language :: Python
Classifier: Programming Language :: Python :: 3
Classifier: Programming Language :: Python :: 3 :: Only
Classifier: Programming Language :: Python :: 3.8
Classifier: Programming Language :: Python :: 3.9
Classifier: Programming Language :: Python :: 3.10
Classifier: Programming Language :: Python :: 3.11
Classifier: Programming Language :: Python :: 3.12
Classifier: Typing :: Typed
Requires-Python: >=3.8
Provides-Extra: dev
Requires-Dist: mypy>=1.11.0; extra == 'dev'
Requires-Dist: pytest>=7.0; extra == 'dev'
Requires-Dist: ruff>=0.5.7; extra == 'dev'
Provides-Extra: test
Requires-Dist: pytest>=7.0; extra == 'test'
Provides-Extra: yaml
Requires-Dist: pyyaml>=6.0; extra == 'yaml'
